simpleqlearn/__init__.py
simpleqlearn/core.py
simpleqlearn-0.1.1.dist-info/licenses/LICENSE
simpleqlearn-0.1.1.dist-info/METADATA
simpleqlearn-0.1.1.dist-info/WHEEL
simpleqlearn-0.1.1.dist-info/top_level.txt
simpleqlearn-0.1.1.dist-info/RECORD
